# Задание 1 
### 11 0 LOAD_FAST 0 (x)

   Описание: Загрузка значения переменной x из локальных переменных в стек. Индекс 0 указывает на первую локальную переменную.

   Эквивалентное выражение на Python: x

### 2 LOAD_CONST 1 (10)

   Описание: Загрузка константы 10 в стек.

   Эквивалент: 10

### 4 BINARY_MULTIPLY

   Описание: Извлечение и перемножение двух верхних значений из стека. Результат помещается обратно в стек.

   Эквивалент: x * 10

### 6 LOAD_CONST 2 (42)

   Описание: Загрузка константы 42 в стек.

   Эквивалент: 42

### 8 BINARY_ADD

   Описание: Извлечение и сложение двух верхних значений из стека. Результат помещается обратно в стек.

   Эквивалент: (x * 10) + 42

### 10 RETURN_VALUE

   Описание: Возврат верхнего значения из стека.

   Эквивалент: Возврат результата (x * 10) + 42.

Итоговое эквивалентное выражение выглядит следующим образом:

result = (x * 10) + 42

# Задание 2
### 0 LOAD_CONST 1 (1)

   Загрузка константы 1 в стек.

### 2 STORE_FAST 1 (r)

   Сохранение значения 1 в локальной переменной r.

### 4 LOAD_FAST 0 (n)

   Загрузка значения переменной n из локальных переменных в стек.

### 6 LOAD_CONST 1 (1)

   Загрузка константы 1 в стек.

### 8 COMPARE_OP 4 (>)

   Сравнение значения n с 1. Если n больше 1, то результат сравнения будет истинным, иначе ложным.

### 10 POP_JUMP_IF_FALSE 30

   Если результат сравнения оказался ложным, происходит переход к инструкции 30.

### 12 LOAD_FAST 1 (r)

   Загрузка текущего значения r из локальных переменных в стек.

### 14 LOAD_FAST 0 (n)

   Загрузка текущего значения n.

### 16 INPLACE_MULTIPLY

   Извлечение и перемножение двух верхних значений из стека, т.е. r и n. Результат сохраняется в первый операнд, т.е. r *= n.

### 20 LOAD_FAST 0 (n)

   Загрузка текущего значения n.

### 22 LOAD_CONST 1 (1)

   Загрузка константы 1 в стек.

### 24 INPLACE_SUBTRACT

   Извлечение двух верхних значений из стека, вычитание первого из второго. Сохранение результата во второй операнд. Т.е. n -= 1.

### 26 STORE_FAST 0 (n)

   Сохранение нового значения n.

### 28 JUMP_ABSOLUTE 4

  Переход к инструкции 4.

### 30 LOAD_FAST 1 (r)

   Загрузка окончательного значения r.

### 32 RETURN_VALUE

   Возврат значения r.

### Данная функция реализует алгоритм вычисления факториала числа n. 
```Python
def factorial(n):
    r = 1
    while n > 1:
        r *= n
        n -= 1
    return r
```
# Задание 3
### Байткод по задаче №1
0: iload_1
1: bipush 10
3: imul
4: bipush 42
6: iadd
7: ireturn
### Байткод по задаче №2
0: iconst_1
1: istore_1
2: iload_0
3: iconst_1
4: if_icmple 14
5: iload_1
6: iload_0
7: imul
8: istore_1
9: iload_0
10: iconst_1
11: isub
12: istore_0
13: goto 2
14: iload_1
15: ireturn
